mawk/__init__.py
mawk/py.typed
mawk-0.1.5.dist-info/METADATA
mawk-0.1.5.dist-info/WHEEL
mawk-0.1.5.dist-info/licenses/LICENSE
mawk-0.1.5.dist-info/RECORD
