Metadata-Version: 2.4
Name: mawk
Version: 0.1.5
Summary: A minimalist implementation of an Awk-like model in Python
License-File: LICENSE
Author: Johan Hidding
Author-email: j.hidding@esciencecenter.nl
Requires-Python: >=3.12,<4
Classifier: Development Status :: 3 - Alpha
Classifier: Intended Audience :: Developers
Classifier: License :: OSI Approved :: Apache Software License
Classifier: Topic :: Software Development
Classifier: Topic :: Utilities
Project-URL: Repository, https://github.com/jhidding/mawk
